bitsandbytes_intel/__init__.py
bitsandbytes_intel/__main__.py
bitsandbytes_intel/cpu_xpu_common.py
bitsandbytes_intel/ops.py
bitsandbytes_intel-0.0.1.dev0.dist-info/licenses/LICENSE
bitsandbytes_intel-0.0.1.dev0.dist-info/METADATA
bitsandbytes_intel-0.0.1.dev0.dist-info/WHEEL
bitsandbytes_intel-0.0.1.dev0.dist-info/entry_points.txt
bitsandbytes_intel-0.0.1.dev0.dist-info/top_level.txt
bitsandbytes_intel-0.0.1.dev0.dist-info/RECORD
