Metadata-Version: 2.4
Name: bitsandbytes-intel
Version: 0.0.1.dev0
Summary: Intel-optimized version of bitsandbytes
Maintainer-email: Titus von Köller <titus@huggingface.co>, Matthew Douglas <matthew.douglas@huggingface.co>
License: MIT
Project-URL: Homepage, https://github.com/bitsandbytes-foundation/bitsandbytes-intel
Project-URL: Bug Tracker, https://github.com/bitsandbytes-foundation/bitsandbytes-intel/issues
Classifier: Development Status :: 4 - Beta
Classifier: License :: OSI Approved :: MIT License
Classifier: Environment :: GPU :: NVIDIA CUDA :: 11
Classifier: Environment :: GPU :: NVIDIA CUDA :: 12
Classifier: Intended Audience :: Developers
Classifier: Intended Audience :: Science/Research
Classifier: Operating System :: POSIX :: Linux
Classifier: Operating System :: Microsoft :: Windows
Classifier: Programming Language :: C++
Classifier: Programming Language :: Python :: Implementation :: CPython
Classifier: Programming Language :: Python :: 3.9
Classifier: Programming Language :: Python :: 3.10
Classifier: Programming Language :: Python :: 3.11
Classifier: Programming Language :: Python :: 3.12
Classifier: Programming Language :: Python :: 3.13
Classifier: Topic :: Scientific/Engineering :: Artificial Intelligence
Requires-Python: >=3.9
License-File: LICENSE
Requires-Dist: bitsandbytes
Requires-Dist: numpy>=1.20.0
Requires-Dist: torch<3,>=2.2
Provides-Extra: dev
Requires-Dist: build<2,>=1.0.0; extra == "dev"
Requires-Dist: ruff==0.11.2; extra == "dev"
Requires-Dist: pre-commit<4,>=3.5.0; extra == "dev"
Requires-Dist: wheel<1,>=0.42; extra == "dev"
Provides-Extra: test
Requires-Dist: pytest~=8.3; extra == "test"
Dynamic: license-file
